gresecml/__init__.py
gresecml/__main__.py
gresecml/commands/__init__.py
gresecml/commands/tensorflow_group.py
gresecml/core/__init__.py
gresecml/core/output_manager.py
gresecml/core/pcap_manager.py
gresecml/core/progress_manager.py
gresecml/core/session_manager.py
gresecml/core/sniffer_manager.py
gresecml/core/tensorflow_prediction_manager.py
gresecml/ml_models/tensorflow.keras
gresecml/ml_models/tensorflow_old.keras
gresecml/models/__init__.py
gresecml/models/gre_packet.py
gresecml/models/gre_session.py
gresecml-0.2.5.dist-info/entry_points.txt
gresecml-0.2.5.dist-info/METADATA
gresecml-0.2.5.dist-info/WHEEL
gresecml-0.2.5.dist-info/RECORD
