Metadata-Version: 2.3
Name: gresecml
Version: 0.2.5
Summary: A small CLI security toolkit
Author: Mathias Greisen
Requires-Python: >=3.13,<4
Classifier: Programming Language :: Python :: 3
Classifier: Programming Language :: Python :: 3.13
Requires-Dist: click (>=8.2.1,<9.0.0)
Requires-Dist: keras (>=3.11.3,<4.0.0)
Requires-Dist: pandas (>=2.3.2,<3.0.0)
Requires-Dist: pyfiglet (>=1.0.4,<2.0.0)
Requires-Dist: rich (>=14.1.0,<15.0.0)
Requires-Dist: scapy (>=2.6.1,<3.0.0)
Requires-Dist: tensorflow (>=2.20.0,<3.0.0)
